entrylogger/__init__.py
entrylogger/main.py
entrylogger-0.1.6.dist-info/licenses/LICENSE
entrylogger-0.1.6.dist-info/METADATA
entrylogger-0.1.6.dist-info/WHEEL
entrylogger-0.1.6.dist-info/top_level.txt
entrylogger-0.1.6.dist-info/RECORD
