Metadata-Version: 2.4
Name: entrylogger
Version: 0.1.6
Summary: A Python module to log workspace entries
Author-email: Hadin Abdul Hameed <libapayapura+git@gmail.com>
License:                     GNU GENERAL PUBLIC LICENSE
Requires-Python: >=3.6
License-File: LICENSE
Requires-Dist: python-dotenv
Requires-Dist: supabase
Dynamic: license-file
